spyder_notebook/__init__.py
spyder_notebook/_version.py
spyder_notebook/config.py
spyder_notebook/confpage.py
spyder_notebook/notebookplugin.py
spyder_notebook/locale/de/LC_MESSAGES/spyder_notebook.mo
spyder_notebook/locale/es/LC_MESSAGES/spyder_notebook.mo
spyder_notebook/locale/fr/LC_MESSAGES/spyder_notebook.mo
spyder_notebook/locale/hr/LC_MESSAGES/spyder_notebook.mo
spyder_notebook/locale/hu/LC_MESSAGES/spyder_notebook.mo
spyder_notebook/locale/ja/LC_MESSAGES/spyder_notebook.mo
spyder_notebook/locale/pl/LC_MESSAGES/spyder_notebook.mo
spyder_notebook/locale/pt_BR/LC_MESSAGES/spyder_notebook.mo
spyder_notebook/locale/ru/LC_MESSAGES/spyder_notebook.mo
spyder_notebook/locale/zh_CN/LC_MESSAGES/spyder_notebook.mo
spyder_notebook/server/__init__.py
spyder_notebook/server/__main__.py
spyder_notebook/server/kernelspec.py
spyder_notebook/server/main.py
spyder_notebook/server/notebook-template.html
spyder_notebook/server/app/build/themes/@jupyterlab/theme-dark-extension/index.css
spyder_notebook/server/app/build/themes/@jupyterlab/theme-light-extension/index.css
spyder_notebook/server/node_modules/katex/src/fonts/generate_fonts.py
spyder_notebook/server/node_modules/katex/src/metrics/extract_tfms.py
spyder_notebook/server/node_modules/katex/src/metrics/extract_ttfs.py
spyder_notebook/server/node_modules/katex/src/metrics/format_json.py
spyder_notebook/server/node_modules/katex/src/metrics/parse_tfm.py
spyder_notebook/server/node_modules/node-gyp/update-gyp.py
spyder_notebook/server/node_modules/node-gyp/gyp/gyp_main.py
spyder_notebook/server/node_modules/node-gyp/gyp/test_gyp.py
spyder_notebook/server/node_modules/node-gyp/gyp/pylib/gyp/MSVSNew.py
spyder_notebook/server/node_modules/node-gyp/gyp/pylib/gyp/MSVSProject.py
spyder_notebook/server/node_modules/node-gyp/gyp/pylib/gyp/MSVSSettings.py
spyder_notebook/server/node_modules/node-gyp/gyp/pylib/gyp/MSVSSettings_test.py
spyder_notebook/server/node_modules/node-gyp/gyp/pylib/gyp/MSVSToolFile.py
spyder_notebook-0.7.1.dist-info/licenses/LICENSE
spyder_notebook-0.7.1.dist-info/METADATA
spyder_notebook-0.7.1.dist-info/WHEEL
spyder_notebook-0.7.1.dist-info/entry_points.txt
spyder_notebook-0.7.1.dist-info/top_level.txt
spyder_notebook-0.7.1.dist-info/RECORD
