Metadata-Version: 2.4
Name: spyder-notebook
Version: 0.7.1
Summary: Jupyter notebook integration with Spyder
Home-page: https://github.com/spyder-ide/spyder-notebook
Author: Spyder Development Team
License: MIT
Keywords: spyder jupyter notebook
Classifier: Development Status :: 4 - Beta
Classifier: Framework :: Jupyter
Classifier: Intended Audience :: Developers
Classifier: License :: OSI Approved :: MIT License
Classifier: Operating System :: OS Independent
Classifier: Programming Language :: Python :: 3
Requires-Python: >=3.9
License-File: LICENSE
Requires-Dist: spyder<6.2,>=6.1
Requires-Dist: nbformat
Requires-Dist: notebook<7.5,>=7.4.7
Requires-Dist: psutil
Requires-Dist: qtpy
Requires-Dist: qdarkstyle
Requires-Dist: requests
Requires-Dist: tornado
Requires-Dist: traitlets
Dynamic: author
Dynamic: classifier
Dynamic: description
Dynamic: description-content-type
Dynamic: home-page
Dynamic: keywords
Dynamic: license
Dynamic: license-file
Dynamic: requires-dist
Dynamic: requires-python
Dynamic: summary
